nonebot_plugin_runagain/__init__.py
nonebot_plugin_runagain-0.1.1.dist-info/LICENSE
nonebot_plugin_runagain-0.1.1.dist-info/METADATA
nonebot_plugin_runagain-0.1.1.dist-info/WHEEL
nonebot_plugin_runagain-0.1.1.dist-info/top_level.txt
nonebot_plugin_runagain-0.1.1.dist-info/RECORD
