Metadata-Version: 2.1
Name: nonebot-plugin-runagain
Version: 0.1.1
Summary: 适用于 NoneBot2 实例的停机与重启控制插件
Author-email: HivertMoZara <worldmozara@163.com>
License: MIT
Project-URL: Homepage, https://github.com/NCBM/nonebot-plugin-runagain
Project-URL: Repository, https://github.com/NCBM/nonebot-plugin-runagain
Requires-Python: <4,>=3.9
License-File: LICENSE
Requires-Dist: nonebot2 >=2.2.0
